{
  "uid": {
    "__TYPE__": "UIDContent",
    "value": "new"
  },
  "text": {
    "__TYPE__": "StructuredTextContent",
    "value": [
      {
        "type": "paragraph",
        "content": {
          "text": "Laborum anim id ex dolore mollit pariatur incididunt adipisicing incididunt sint commodo nisi fugiat irure. Velit commodo consequat enim deserunt quis."
        }
      }
    ]
  },
  "tableRow": {
    "__TYPE__": "GroupContentType",
    "value": [
      {
        "__TYPE__": "GroupItemContent",
        "value": [
          [
            "field1",
            {
              "__TYPE__": "StructuredTextContent",
              "value": [
                {
                  "type": "paragraph",
                  "content": {
                    "text": "Nulla elit qui pariatur cupidatat adipisicing commodo ullamco esse culpa. Ea reprehenderit exercitation eu esse est labore quis irure eiusmod mollit Lorem qui. Enim adipisicing officia duis cupidatat deserunt adipisicing mollit nisi qui laboris in anim minim aliquip."
                  }
                }
              ]
            }
          ],
          [
            "field2",
            {
              "__TYPE__": "StructuredTextContent",
              "value": [
                {
                  "type": "paragraph",
                  "content": {
                    "text": "Lorem eiusmod laboris laborum exercitation ullamco esse laborum velit. Dolor ullamco adipisicing cillum aliqua nulla do eiusmod tempor. Reprehenderit deserunt magna anim in et do cupidatat ea."
                  }
                }
              ]
            }
          ],
          [
            "field3",
            {
              "__TYPE__": "StructuredTextContent",
              "value": [
                {
                  "type": "paragraph",
                  "content": {
                    "text": "Eiusmod laboris amet deserunt reprehenderit ex velit dolore est non nisi nulla veniam officia excepteur. Adipisicing veniam non aliqua pariatur adipisicing anim. Ut aliquip est exercitation sit id sit ex laboris culpa."
                  }
                }
              ]
            }
          ]
        ]
      }
    ]
  },
  "slices": {
    "__TYPE__": "SliceContentType",
    "value": [
      {
        "key": "text_block$5ff3fc9e-0be5-485e-9ab1-0659fc8058ff",
        "name": "text_block",
        "widget": {
          "__TYPE__": "SharedSliceContent",
          "variation": "default-slice",
          "primary": {
            "text": {
              "__TYPE__": "StructuredTextContent",
              "value": [
                {
                  "type": "paragraph",
                  "content": {
                    "text": "Aute ad excepteur amet irure pariatur ut id irure laboris Lorem officia ullamco."
                  }
                }
              ]
            }
          },
          "items": [
            {
              "__TYPE__": "GroupItemContent",
              "value": []
            }
          ]
        }
      }
    ]
  }
}